Metadata-Version: 1.1
Name: textgraphics
Version: 0.20
Summary: A Python Package for Graphical Methods in Text Analysis
Home-page: https://github.com/Jverma/TextGraphics
Author: Janu Verma
Author-email: jv367@cornell.edu
License: MIT
Keywords: Genomics,Quantitative genetics,java
Platform: Linux
Platform: Mac OSX
Platform: Windows
Platform: Unix
Classifier: Development Status :: 3 - Alpha
Classifier: Intended Audience :: Developers
Classifier: Intended Audience :: Science/Research
Classifier: Operating System :: OS Independent
Classifier: Programming Language :: Python
